watson_embed_model_packager/__init__.py
watson_embed_model_packager/__main__.py
watson_embed_model_packager/build_model_images.py
watson_embed_model_packager/common_args.py
watson_embed_model_packager/constants.py
watson_embed_model_packager/setup_build_config.py
watson_embed_model_packager/resources/artifactory.dockerfile
watson_embed_model_packager/resources/copy_bin_with_libs.sh
watson_embed_model_packager/resources/local.dockerfile
watson_embed_model_packager/resources/unpack_model.sh
watson_embed_model_packager-0.10.8.data/data/artifactory.dockerfile
watson_embed_model_packager-0.10.8.data/data/copy_bin_with_libs.sh
watson_embed_model_packager-0.10.8.data/data/local.dockerfile
watson_embed_model_packager-0.10.8.data/data/unpack_model.sh
watson_embed_model_packager-0.10.8.dist-info/LICENSE
watson_embed_model_packager-0.10.8.dist-info/METADATA
watson_embed_model_packager-0.10.8.dist-info/WHEEL
watson_embed_model_packager-0.10.8.dist-info/top_level.txt
watson_embed_model_packager-0.10.8.dist-info/RECORD
